{"slug":"pr-tool","title":"PR Tool","released":"2020-07","content":"<p>Met de <a href=\"https://azure-prs.herokuapp.com/\">PR tool</a> kun je pull-requests van <a href=\"http://dev.azure.com/\">Azure DevOps</a>, <a href=\"http://bitbucket.org/\">Bitbucket</a> &amp; <a href=\"https://about.gitlab.com\">Gitlab</a> op één plaats terugzien.\nDeze app toont het aantal PR&#39;s dat aandacht nodig heeft direct in de macOS menubalk als actieve reminder.</p>\n<p>Voor deze (macOS) tool heb ik het concept, design &amp; de implementatie uitgevoerd.</p>\n<p>Het kwam regelmatig voor dat PR e-mails over het hoofd werden gezien, of dat er begonnen was aan een review, maar deze niet afgerond (approved) werden. Hierdoor waren collega&#39;s onnodig op mij aan het wachten en vice-versa.</p>\n<p>Deze app is gemaakt in <a href=\"https://www.electronjs.org/\">Electron</a> en zijn de designs gemaakt in <a href=\"https://figma.com\">Figma</a>.</p>\n","before":"mauna","after":"omroep-brabant","image":{"src":"/build/img/pr-tool.png","width":2012,"height":1248}}